oauthsub/__init__.py
oauthsub/__main__.py
oauthsub/auth_service.py
oauthsub/configuration.py
oauthsub/util.py
oauthsub/templates/layout.html.tpl
oauthsub/templates/message.html.tpl
oauthsub-0.2.1.dist-info/LICENSE
oauthsub-0.2.1.dist-info/METADATA
oauthsub-0.2.1.dist-info/WHEEL
oauthsub-0.2.1.dist-info/entry_points.txt
oauthsub-0.2.1.dist-info/top_level.txt
oauthsub-0.2.1.dist-info/RECORD
