Metadata-Version: 2.1
Name: oauthsub
Version: 0.2.1
Summary: Simple oauth2 subrequest handler for nginx
Home-page: https://github.com/cheshirekow/oauthsub
Author: Josh Bialkowski
Author-email: josh.bialkowski@gmail.com
License: UNKNOWN
Download-URL: https://github.com/cheshirekow/oauthsub/archive/0.2.1.tar.gz
Keywords: oauth,nginx,flask
Platform: UNKNOWN
Requires-Dist: flask
Requires-Dist: jinja2
Requires-Dist: requests-oauthlib
